talive/__init__.py
talive/basic.py
talive/momentum.py
talive/trend.py
talive/volatility.py
talive-0.1.0.dist-info/LICENSE
talive-0.1.0.dist-info/WHEEL
talive-0.1.0.dist-info/METADATA
talive-0.1.0.dist-info/RECORD
