Metadata-Version: 2.1
Name: talive
Version: 0.1.0
Summary: Technical Analysis for LIVE trading
Author: Zou Yilin
Author-email: zouyilin2@yandex.com
Requires-Python: >=3.8
Classifier: Programming Language :: Python :: 3
Classifier: Programming Language :: Python :: 3.10
Classifier: Programming Language :: Python :: 3.8
Classifier: Programming Language :: Python :: 3.9
